{
  "total_additions": 8767709,
  "total_deletions": 2866814,
  "total_commits": 362,
  "most_active_month": "2025-03",
  "most_active_month_commits": 239,
  "monthly_data": [
    {
      "month": "2025-05",
      "additions": 67664,
      "deletions": 20077,
      "commits": 72
    },
    {
      "month": "2025-04",
      "additions": 1752800,
      "deletions": 1066922,
      "commits": 50
    },
    {
      "month": "2025-03",
      "additions": 6947222,
      "deletions": 1779815,
      "commits": 239
    },
    {
      "month": "2025-02",
      "additions": 23,
      "deletions": 0,
      "commits": 1
    }
  ],
  "timestamp": "2025-05-04T23:24:58Z"
}